kyg_ggk/__init__.py
kyg_ggk/fastguess.py
kyg_ggk/main.py
kyg_guessing_game_kit-0.1.dist-info/METADATA
kyg_guessing_game_kit-0.1.dist-info/WHEEL
kyg_guessing_game_kit-0.1.dist-info/entry_points.txt
kyg_guessing_game_kit-0.1.dist-info/top_level.txt
kyg_guessing_game_kit-0.1.dist-info/RECORD
