Metadata-Version: 2.4
Name: kyg-guessing-game-kit
Version: 0.1
Summary: KYG: Guessing Game Kit – Playful Python Learning by Ashok Sir and Sathish Ramanujam
Home-page: https://www.ashokbakthavathsalam.com/
Author: Ashok Bakthavathsalam, Sathish Ramanujam
Author-email: ashok@kgisl.com, sathishse13@gmail.com
Keywords: python education game guessing tkinter induction zero2hero
Classifier: Programming Language :: Python :: 3
Classifier: License :: OSI Approved :: MIT License
Classifier: Operating System :: OS Independent
Classifier: Topic :: Education
Classifier: Topic :: Games/Entertainment
Classifier: Intended Audience :: Education
Classifier: Natural Language :: English
Requires-Python: >=3.6
Dynamic: author
Dynamic: author-email
Dynamic: classifier
Dynamic: description
Dynamic: description-content-type
Dynamic: home-page
Dynamic: keywords
Dynamic: requires-python
Dynamic: summary
